incdbscan/__init__.py
incdbscan/_bfscomponentfinder.py
incdbscan/_deleter.py
incdbscan/_inserter.py
incdbscan/_labels.py
incdbscan/_neighbor_searcher.py
incdbscan/_object.py
incdbscan/_objects.py
incdbscan/_utils.py
incdbscan/incrementaldbscan.py
incdbscan/tests/conftest.py
incdbscan/tests/test_deleter.py
incdbscan/tests/test_incrementaldbscan.py
incdbscan/tests/test_inserter.py
incdbscan/tests/test_testutils.py
incdbscan/tests/test_with_data.py
incdbscan/tests/testutils.py
incdbscan-0.3.0.dist-info/LICENSE
incdbscan-0.3.0.dist-info/METADATA
incdbscan-0.3.0.dist-info/WHEEL
incdbscan-0.3.0.dist-info/RECORD
