Metadata-Version: 2.1
Name: incdbscan
Version: 0.3.0
Summary: Implementation of IncrementalDBSCAN clustering.
Home-page: https://github.com/DataOmbudsman/incdbscan
License: BSD-3-Clause
Keywords: clustering,incremental clustering
Author: Arpad Fulop
Author-email: data.ombudsman@mailbox.org
Requires-Python: >=3.9.0,<4.0
Classifier: Development Status :: 4 - Beta
Classifier: Intended Audience :: Developers
Classifier: Intended Audience :: Science/Research
Classifier: License :: OSI Approved :: BSD License
Classifier: Operating System :: OS Independent
Classifier: Programming Language :: Python :: 3
Classifier: Programming Language :: Python :: 3.9
Classifier: Programming Language :: Python :: 3.10
Classifier: Programming Language :: Python :: 3.11
Classifier: Programming Language :: Python :: 3.12
Classifier: Programming Language :: Python :: 3.13
Classifier: Programming Language :: Python :: 3.8
Classifier: Topic :: Scientific/Engineering :: Artificial Intelligence
Requires-Dist: numpy (>=2.0.0,<3.0.0)
Requires-Dist: rustworkx (>=0.15.0,<0.16.0)
Requires-Dist: scikit-learn (>=1.5.0,<2.0.0)
Requires-Dist: sortedcontainers (>=2.4.0,<3.0.0)
Requires-Dist: xxhash (>=3.5.0,<4.0.0)
Project-URL: Repository, https://github.com/DataOmbudsman/incdbscan
